Webstore_ScraperPY/__init__.py
Webstore_ScraperPY/scrape.py
Webstore_ScrapperPY/__init__.py
Webstore_ScrapperPY/scrape.py
Webstore_ScraperPY-0.2.0.dist-info/METADATA
Webstore_ScraperPY-0.2.0.dist-info/WHEEL
Webstore_ScraperPY-0.2.0.dist-info/top_level.txt
Webstore_ScraperPY-0.2.0.dist-info/RECORD
