Metadata-Version: 2.1
Name: Webstore-ScraperPY
Version: 0.2.0
Summary: A Python library for scraping data from Goodwill and Ebay.
Home-page: https://github.com/Scottyboi1/Webstore_Scraper
Author: Scott Avery
Author-email: scottavery2001@gmail.com
Classifier: Programming Language :: Python :: 3
Classifier: License :: OSI Approved :: MIT License
Classifier: Operating System :: OS Independent
Requires-Python: >=3.6
